[
  {
    "_id": {
      "$oid": "6596de946684b23a84353e75"
    },
    "userId": {
      "$oid": "6596de936684b23a84353e72"
    },
    "otp": "13cfc9",
    "expiresAt": {
      "$date": "2024-01-04T17:06:36.093Z"
    },
    "__v": 0
  },
  {
    "_id": {
      "$oid": "65974c6f96cfbfebf12b5484"
    },
    "userId": {
      "$oid": "65974c6f96cfbfebf12b5481"
    },
    "otp": "909ac4",
    "expiresAt": {
      "$date": "2024-01-05T00:55:19.373Z"
    },
    "__v": 0
  },
  {
    "_id": {
      "$oid": "659882e90240498f32df0837"
    },
    "userId": {
      "$oid": "659882e90240498f32df0834"
    },
    "otp": "cd595f",
    "expiresAt": {
      "$date": "2024-01-05T23:00:01.116Z"
    },
    "__v": 0
  },
  {
    "_id": {
      "$oid": "65988796c688e7bf8d60b7d3"
    },
    "userId": {
      "$oid": "65988796c688e7bf8d60b7d0"
    },
    "otp": "6e4b7b",
    "expiresAt": {
      "$date": "2024-01-05T23:19:58.716Z"
    },
    "__v": 0
  },
  {
    "_id": {
      "$oid": "65d2d3eed500e34b2971156d"
    },
    "userId": {
      "$oid": "65d2d3eed500e34b2971156a"
    },
    "otp": "5503fb",
    "expiresAt": {
      "$date": "2024-02-19T04:37:10.796Z"
    },
    "__v": 0
  },
  {
    "_id": {
      "$oid": "66b6448994c084b220b33ef4"
    },
    "userId": {
      "$oid": "66b6448994c084b220b33ef1"
    },
    "otp": "36d5a7",
    "expiresAt": {
      "$date": "2024-08-09T17:02:09.663Z"
    },
    "__v": 0
  }
]